Changelog.md
MANIFEST.in
README.md
setup.py
PyCreator_Core.egg-info/PKG-INFO
PyCreator_Core.egg-info/SOURCES.txt
PyCreator_Core.egg-info/dependency_links.txt
PyCreator_Core.egg-info/top_level.txt
pycreator_core/__init__.py
pycreator_core/analyse.py
pycreator_core/autocompletion.py
pycreator_core/config.json
pycreator_core/config.py
pycreator_core/documentation.py
pycreator_core/execute.py
pycreator_core/filesystem.py
pycreator_core/history.py
pycreator_core/snippets.py
pycreator_core/utils.py